{
  "3": {
    "inputs": {
      "model": [
        "4",
        0
      ],
      "positive": [
        "5",
        0
      ],
      "negative": [
        "6",
        0
      ],
      "latent_image": [
        "9",
        0
      ]
    },
    "class_type": "KSampler"
  },
  "4": {
    "class_type": "CheckpointLoaderSimple"
  },
  "5": {
    "inputs": {
      "clip": [
        "4",
        1
      ]
    },
    "class_type": "CLIPTextEncode"
  },
  "6": {
    "inputs": {
      "clip": [
        "4",
        1
      ]
    },
    "class_type": "CLIPTextEncode"
  },
  "7": {
    "inputs": {
      "samples": [
        "3",
        0
      ],
      "vae": [
        "4",
        2
      ]
    },
    "class_type": "VAEDecode"
  },
  "8": {
    "inputs": {
      "images": [
        "7",
        0
      ]
    },
    "class_type": "SaveImage"
  },
  "9": {
    "class_type": "EmptyLatentImage"
  }
}
